yarabuilder/__init__.py
yarabuilder/yarabuilder.py
yarabuilder/yararule.py
yarabuilder-0.0.6.dist-info/LICENSE
yarabuilder-0.0.6.dist-info/METADATA
yarabuilder-0.0.6.dist-info/WHEEL
yarabuilder-0.0.6.dist-info/top_level.txt
yarabuilder-0.0.6.dist-info/RECORD
